feon/__init__.py
feon/base.py
feon/mesh.py
feon/tools.py
feon/derivation/__init__.py
feon/derivation/base.py
feon/derivation/dElement.py
feon/derivation/integration.py
feon/derivation/lagrange.py
feon/ffa/__init__.py
feon/ffa/element.py
feon/ffa/node.py
feon/ffa/solver.py
feon/ffa/system.py
feon/sa/__init__.py
feon/sa/draw2d.py
feon/sa/element.py
feon/sa/node.py
feon/sa/post_process.py
feon/sa/solver.py
feon/sa/system.py
feon-1.0.3.dist-info/METADATA
feon-1.0.3.dist-info/RECORD
feon-1.0.3.dist-info/WHEEL
feon-1.0.3.dist-info/top_level.txt
