Metadata-Version: 2.1
Name: feon
Version: 1.0.3
Summary: FEA python-based framework
Home-page: https://github.com/YaoyaoBae/Feon
Author: YAOYAO PEI
Author-email: yaoyao.bae@foxmail.com
License: UNKNOWN
Platform: UNKNOWN
Requires-Dist: numpy
